earthquakeupdate/__init__.py
earthquake_news_indonesia-0.1.dist-info/METADATA
earthquake_news_indonesia-0.1.dist-info/WHEEL
earthquake_news_indonesia-0.1.dist-info/top_level.txt
earthquake_news_indonesia-0.1.dist-info/RECORD
